ghidra_bridge/__init__.py
ghidra_bridge/ghidra_bridge.py
ghidra_bridge/install_server.py
ghidra_bridge/test_ghidra_bridge.py
ghidra_bridge/server/__init__.py
ghidra_bridge/server/example_py3_from_ghidra_bridge.py
ghidra_bridge/server/ghidra_bridge_port.py
ghidra_bridge/server/ghidra_bridge_server.py
ghidra_bridge/server/ghidra_bridge_server_background.py
ghidra_bridge/server/ghidra_bridge_server_shutdown.py
ghidra_bridge-1.0.0.dist-info/LICENSE
ghidra_bridge-1.0.0.dist-info/METADATA
ghidra_bridge-1.0.0.dist-info/WHEEL
ghidra_bridge-1.0.0.dist-info/top_level.txt
ghidra_bridge-1.0.0.dist-info/RECORD
