Metadata-Version: 2.1
Name: ghidra-bridge
Version: 1.0.0
Summary: RPC bridge from Python to Ghidra Jython
Home-page: https://github.com/justfoxing/ghidra_bridge
Author: justfoxing
Author-email: justfoxingprojects@gmail.com
Classifier: Programming Language :: Python
Classifier: License :: OSI Approved :: MIT License
Classifier: Operating System :: OS Independent
License-File: LICENSE
